nova/virt/powervm_ext/__init__.py
nova/virt/powervm_ext/driver.py
nova_powervm/__init__.py
nova_powervm/version.py
nova_powervm/conf/__init__.py
nova_powervm/conf/powervm.py
nova_powervm/hacking/__init__.py
nova_powervm/hacking/checks.py
nova_powervm/locale/nova-powervm.pot
nova_powervm/locale/de/nova-powervm.po
nova_powervm/locale/es/nova-powervm.po
nova_powervm/locale/fr/nova-powervm.po
nova_powervm/locale/it/nova-powervm.po
nova_powervm/locale/ja/nova-powervm.po
nova_powervm/locale/ko/nova-powervm.po
nova_powervm/locale/pt-BR/nova-powervm.po
nova_powervm/locale/ru/nova-powervm.po
nova_powervm/locale/zh-Hans/nova-powervm.po
nova_powervm/locale/zh-Hant/nova-powervm.po
nova_powervm/tests/__init__.py
nova_powervm/tests/conf/__init__.py
nova_powervm/tests/conf/test_conf.py
nova_powervm/tests/virt/__init__.py
nova_powervm/tests/virt/powervm/__init__.py
nova_powervm/tests/virt/powervm/fixtures.py
nova_powervm/tests/virt/powervm/test_driver.py
nova_powervm/tests/virt/powervm/test_event.py
nova_powervm/tests/virt/powervm/test_host.py
nova_powervm/tests/virt/powervm/test_image.py
nova_powervm/tests/virt/powervm/test_live_migration.py
nova_powervm/tests/virt/powervm/test_media.py
nova_powervm/tests/virt/powervm/test_mgmt.py
nova_powervm/tests/virt/powervm/test_slot.py
nova_powervm/tests/virt/powervm/test_vif.py
nova_powervm/tests/virt/powervm/test_vm.py
nova_powervm/tests/virt/powervm/disk/__init__.py
nova_powervm/tests/virt/powervm/disk/fake_adapter.py
nova_powervm/tests/virt/powervm/disk/test_driver.py
nova_powervm/tests/virt/powervm/disk/test_imagecache.py
nova_powervm/tests/virt/powervm/disk/test_localdisk.py
nova_powervm/tests/virt/powervm/disk/test_ssp.py
nova_powervm/tests/virt/powervm/nvram/__init__.py
nova_powervm/tests/virt/powervm/nvram/fake_api.py
nova_powervm/tests/virt/powervm/nvram/test_manager.py
nova_powervm/tests/virt/powervm/nvram/test_swift.py
nova_powervm/tests/virt/powervm/tasks/__init__.py
nova_powervm/tests/virt/powervm/tasks/test_image.py
nova_powervm-9.0.0.dist-info/AUTHORS
nova_powervm-9.0.0.dist-info/LICENSE
nova_powervm-9.0.0.dist-info/METADATA
nova_powervm-9.0.0.dist-info/WHEEL
nova_powervm-9.0.0.dist-info/entry_points.txt
nova_powervm-9.0.0.dist-info/pbr.json
nova_powervm-9.0.0.dist-info/top_level.txt
nova_powervm-9.0.0.dist-info/RECORD
