Metadata-Version: 2.1
Name: nova-powervm
Version: 9.0.0
Summary: PowerVM driver for OpenStack Nova.
Home-page: https://nova-powervm.readthedocs.io
Author: OpenStack
Author-email: openstack-discuss@lists.openstack.org
License: UNKNOWN
Platform: UNKNOWN
Classifier: Environment :: OpenStack
Classifier: Intended Audience :: Information Technology
Classifier: Intended Audience :: System Administrators
Classifier: License :: OSI Approved :: Apache Software License
Classifier: Operating System :: POSIX :: Linux
Classifier: Programming Language :: Python
Classifier: Programming Language :: Python :: 2
Classifier: Programming Language :: Python :: 2.7
Classifier: Programming Language :: Python :: 3
Classifier: Programming Language :: Python :: 3.6
Requires-Dist: pbr (!=2.1.0,>=2.0.0)
Requires-Dist: Babel (!=2.4.0,>=2.3.4)
Requires-Dist: six (>=1.10.0)
Requires-Dist: oslo.config (>=6.1.0)
Requires-Dist: oslo.log (>=3.36.0)
Requires-Dist: oslo.serialization (!=2.19.1,>=2.21.1)
Requires-Dist: oslo.utils (>=3.37.0)
Requires-Dist: os-resource-classes (>=0.1.0)
Requires-Dist: pypowervm (>=1.1.20)
Requires-Dist: python-swiftclient (>=3.2.0)
Requires-Dist: taskflow (>=2.16.0)
Requires-Dist: setuptools (!=24.0.0,!=34.0.0,!=34.0.1,!=34.0.2,!=34.0.3,!=34.1.0,!=34.1.1,!=34.2.0,!=34.3.0,!=34.3.1,!=34.3.2,!=36.2.0,>=21.0.0)
Requires-Dist: sphinx (!=1.6.6,!=1.6.7,<2.0.0,>=1.6.2) ; (python_version=='2.7')
Requires-Dist: sphinx (!=1.6.6,!=1.6.7,!=2.1.0,>=1.6.2) ; (python_version>='3.4')
